arkham_sdk_python/__init__.py
arkham_sdk_python/client.py
arkham_sdk_python/exceptions.py
arkham_sdk_python/keypair.py
arkham_sdk_python/models.py
arkham_sdk_python/signer.py
arkham_sdk_python/ws_client.py
arkham_sdk_python-0.1.2.dist-info/licenses/LICENSE.md
arkham_sdk_python-0.1.2.dist-info/METADATA
arkham_sdk_python-0.1.2.dist-info/WHEEL
arkham_sdk_python-0.1.2.dist-info/top_level.txt
arkham_sdk_python-0.1.2.dist-info/RECORD
