Metadata-Version: 2.4
Name: arkham-sdk-python
Version: 0.1.2
Summary: Python SDK for Arkham Exchange API
Author-email: Arkham Intelligence <support@arkm.com>
Maintainer-email: Arkham Intelligence <support@arkm.com>
License: MIT License
Project-URL: Homepage, https://github.com/arkhamintelligence/arkham-sdk-python
Project-URL: Repository, https://github.com/arkhamintelligence/arkham-sdk-python
Project-URL: Bug Tracker, https://github.com/arkhamintelligence/arkham-sdk-python/issues
Keywords: arkham,exchange,api,sdk,trading,cryptocurrency
Classifier: Development Status :: 3 - Alpha
Classifier: Intended Audience :: Developers
Classifier: License :: OSI Approved :: MIT License
Classifier: Operating System :: OS Independent
Classifier: Programming Language :: Python :: 3
Classifier: Programming Language :: Python :: 3.8
Classifier: Programming Language :: Python :: 3.9
Classifier: Programming Language :: Python :: 3.10
Classifier: Programming Language :: Python :: 3.11
Classifier: Programming Language :: Python :: 3.12
Classifier: Topic :: Software Development :: Libraries :: Python Modules
Classifier: Topic :: Internet :: WWW/HTTP :: Dynamic Content
Classifier: Topic :: Office/Business :: Financial
Requires-Python: >=3.8
License-File: LICENSE.md
Requires-Dist: requests>=2.25.0
Requires-Dist: websocket-client>=1.0.0
Requires-Dist: typing_extensions>=4.0.0
Provides-Extra: dev
Requires-Dist: black>=22.0.0; extra == "dev"
Requires-Dist: flake8>=5.0.0; extra == "dev"
Requires-Dist: mypy>=1.0.0; extra == "dev"
Requires-Dist: isort>=5.0.0; extra == "dev"
Requires-Dist: pre-commit>=2.20.0; extra == "dev"
Provides-Extra: test
Requires-Dist: responses>=0.20.0; extra == "test"
Provides-Extra: docs
Requires-Dist: sphinx>=5.0.0; extra == "docs"
Requires-Dist: sphinx-rtd-theme>=1.0.0; extra == "docs"
Requires-Dist: myst-parser>=0.18.0; extra == "docs"
Dynamic: license-file
